mdseo/__init__.py
mdseo/_nbdev.py
mdseo/core.py
mdseo-0.0.19.dist-info/LICENSE
mdseo-0.0.19.dist-info/METADATA
mdseo-0.0.19.dist-info/WHEEL
mdseo-0.0.19.dist-info/entry_points.txt
mdseo-0.0.19.dist-info/top_level.txt
mdseo-0.0.19.dist-info/RECORD
