Metadata-Version: 2.1
Name: mdseo
Version: 0.0.19
Summary: Analyze Markdown Documents Used In Static Sites For SEO
Home-page: https://github.com/outerbounds/mdseo/tree/master/
Author: Hamel Husain
Author-email: hamel@outerbounds.co
License: Apache Software License 2.0
Keywords: seo markdown
Platform: UNKNOWN
Classifier: Development Status :: 3 - Alpha
Classifier: Intended Audience :: Developers
Classifier: Natural Language :: English
Classifier: Programming Language :: Python :: 3.7
Classifier: Programming Language :: Python :: 3.8
Classifier: Programming Language :: Python :: 3.9
Classifier: Programming Language :: Python :: 3.10
Classifier: License :: OSI Approved :: Apache Software License
Requires-Python: >=3.7
License-File: LICENSE
Requires-Dist: pip
Requires-Dist: packaging
Requires-Dist: pyyaml (==6.0)
Requires-Dist: fastcore (>=1.4.2)
Provides-Extra: dev
